timedc/__init__.py
timedc/core.py
timedc-0.1.3.dist-info/licenses/LICENSE
timedc-0.1.3.dist-info/METADATA
timedc-0.1.3.dist-info/WHEEL
timedc-0.1.3.dist-info/top_level.txt
timedc-0.1.3.dist-info/RECORD
