Metadata-Version: 2.4
Name: timedc
Version: 0.1.3
Summary: Утилита для генерации Discord timestamp
Author: Prostoron
License: MIT License
Requires-Python: >=3.10
License-File: LICENSE
Dynamic: license-file
